formulallm/__init__.py
formulallm/formula_agent.py
formulallm/formula_program.py
formulallm/formula_tools.py
formulallm/prompts.py
formulallm-0.1.1.dist-info/LICENSE
formulallm-0.1.1.dist-info/METADATA
formulallm-0.1.1.dist-info/WHEEL
formulallm-0.1.1.dist-info/RECORD
